wuodan/init.py
wuodan/wuodan.py
wuodan-0.1.2.dist-info/METADATA
wuodan-0.1.2.dist-info/WHEEL
wuodan-0.1.2.dist-info/entry_points.txt
wuodan-0.1.2.dist-info/top_level.txt
wuodan-0.1.2.dist-info/RECORD
